knowit/__init__.py
knowit/__main__.py
knowit/api.py
knowit/config.py
knowit/core.py
knowit/defaults.yml
knowit/properties/__init__.py
knowit/properties/audio.py
knowit/properties/general.py
knowit/properties/subtitle.py
knowit/properties/video.py
knowit/provider.py
knowit/providers/__init__.py
knowit/providers/enzyme.py
knowit/providers/ffmpeg.py
knowit/providers/mediainfo.py
knowit/providers/mkvmerge.py
knowit/rules/__init__.py
knowit/rules/audio.py
knowit/rules/general.py
knowit/rules/subtitle.py
knowit/rules/video.py
knowit/serializer.py
knowit/units.py
knowit/utils.py
knowit-0.5.10.dist-info/LICENSE
knowit-0.5.10.dist-info/METADATA
knowit-0.5.10.dist-info/WHEEL
knowit-0.5.10.dist-info/entry_points.txt
knowit-0.5.10.dist-info/RECORD
